bcforms/__init__.py
bcforms/__main__.py
bcforms/_version.py
bcforms/core.py
bcforms/grammar.lark
bcforms/rest.py
bcforms/web/app.css
bcforms/web/app.js
bcforms/web/index.html
bcforms-0.0.9.dist-info/LICENSE
bcforms-0.0.9.dist-info/METADATA
bcforms-0.0.9.dist-info/WHEEL
bcforms-0.0.9.dist-info/entry_points.txt
bcforms-0.0.9.dist-info/top_level.txt
bcforms-0.0.9.dist-info/RECORD
