Metadata-Version: 2.1
Name: bcforms
Version: 0.0.9
Summary: Toolkit for concretely describing macromolecular complexes
Home-page: https://github.com/KarrLab/bcforms
Author: Karr Lab
Author-email: info@karrlab.org
License: MIT
Download-URL: https://github.com/KarrLab/bcforms
Keywords: complex post-translational modification crosslinks systems biology
Platform: UNKNOWN
Classifier: Development Status :: 3 - Alpha
Classifier: License :: OSI Approved :: MIT License
Classifier: Programming Language :: Python
Requires-Dist: bpforms (>=0.0.15)
Requires-Dist: cement (>=3.0.0)
Requires-Dist: lark-parser (>=0.6.6)
Requires-Dist: openbabel (<3)
Requires-Dist: setuptools
Requires-Dist: wc-utils[chem] (>=0.0.14)
Provides-Extra: all
Requires-Dist: capturer ; extra == 'all'
Requires-Dist: flask ; extra == 'all'
Requires-Dist: flask-restplus ; extra == 'all'
Requires-Dist: mock ; extra == 'all'
Requires-Dist: sphinx (>=1.8) ; extra == 'all'
Requires-Dist: sphinx-fontawesome ; extra == 'all'
Requires-Dist: sphinx-rtd-theme (>=0.4.2) ; extra == 'all'
Requires-Dist: sphinxcontrib-addmetahtml (>=0.1.1) ; extra == 'all'
Requires-Dist: sphinxcontrib-bibtex ; extra == 'all'
Requires-Dist: sphinxcontrib-googleanalytics (>=0.1.1) ; extra == 'all'
Requires-Dist: sphinxcontrib-spelling ; extra == 'all'
Requires-Dist: sphinxprettysearchresults ; extra == 'all'
Requires-Dist: wc-utils[protonation] (>=0.0.15) ; extra == 'all'
Provides-Extra: docs
Requires-Dist: sphinx (>=1.8) ; extra == 'docs'
Requires-Dist: sphinx-fontawesome ; extra == 'docs'
Requires-Dist: sphinx-rtd-theme (>=0.4.2) ; extra == 'docs'
Requires-Dist: sphinxcontrib-addmetahtml (>=0.1.1) ; extra == 'docs'
Requires-Dist: sphinxcontrib-bibtex ; extra == 'docs'
Requires-Dist: sphinxcontrib-googleanalytics (>=0.1.1) ; extra == 'docs'
Requires-Dist: sphinxcontrib-spelling ; extra == 'docs'
Requires-Dist: sphinxprettysearchresults ; extra == 'docs'
Provides-Extra: draw
Requires-Dist: wc-utils[protonation] (>=0.0.15) ; extra == 'draw'
Provides-Extra: rest_api
Requires-Dist: flask ; extra == 'rest_api'
Requires-Dist: flask-restplus ; extra == 'rest_api'
Provides-Extra: tests
Requires-Dist: capturer ; extra == 'tests'
Requires-Dist: mock ; extra == 'tests'
